vsengine/__init__.py
vsengine/_futures.py
vsengine/_helpers.py
vsengine/_hospice.py
vsengine/_nodes.py
vsengine/_testutils.py
vsengine/convert.py
vsengine/loops.py
vsengine/policy.py
vsengine/video.py
vsengine/vpy.py
vsengine/adapters/__init__.py
vsengine/adapters/asyncio.py
vsengine/adapters/trio.py
vsengine-0.1.1.dist-info/COPYING
vsengine-0.1.1.dist-info/WHEEL
vsengine-0.1.1.dist-info/METADATA
vsengine-0.1.1.dist-info/RECORD
