Metadata-Version: 2.1
Name: vsengine
Version: 0.1.1
Summary: vsengine - A common set of function that bridge vapoursynth with your application.
Author-email: cid-chan <cid+git@cid-chan.moe>
Requires-Python: >=3.9
Requires-Dist: vapoursynth>=57
Requires-Dist: trio ; extra == "trio"
Provides-Extra: trio
